README.md
setup.py
undeniable/__init__.py
undeniable/server.py
undeniable.egg-info/PKG-INFO
undeniable.egg-info/SOURCES.txt
undeniable.egg-info/dependency_links.txt
undeniable.egg-info/top_level.txt
undeniable/core/__init__.py
undeniable/core/ipfs.py
undeniable/core/solana.py
undeniable/protocol/__init__.py
undeniable/protocol/spec.json
undeniable/protocol/undeniable.py